pkg_96638/__init__.py
pkg_96638/__main__.py
pkg_96638/run.py
pkg_96638-1.0.0.dist-info/licenses/LICENSE
pkg_96638-1.0.0.dist-info/METADATA
pkg_96638-1.0.0.dist-info/WHEEL
pkg_96638-1.0.0.dist-info/entry_points.txt
pkg_96638-1.0.0.dist-info/top_level.txt
pkg_96638-1.0.0.dist-info/RECORD
